visio2img/__init__.py
visio2img/visio2img.py
visio2img-1.3.0.dist-info/DESCRIPTION.rst
visio2img-1.3.0.dist-info/METADATA
visio2img-1.3.0.dist-info/RECORD
visio2img-1.3.0.dist-info/WHEEL
visio2img-1.3.0.dist-info/entry_points.txt
visio2img-1.3.0.dist-info/metadata.json
visio2img-1.3.0.dist-info/top_level.txt
