Metadata-Version: 2.0
Name: visio2img
Version: 1.3.0
Summary: MS-Visio file (.vsd, .vsdx) to images converter
Home-page: https://github.com/visio2img/visio2img
Author: Takeshi KOMIYA
Author-email: i.tkomiya@gmail.com
License: UNKNOWN
Platform: UNKNOWN
Classifier: Development Status :: 4 - Beta
Classifier: Environment :: Console
Classifier: Environment :: Win32 (MS Windows)
Classifier: Intended Audience :: System Administrators
Classifier: License :: OSI Approved :: Apache Software License
Classifier: Operating System :: Microsoft :: Windows
Classifier: Programming Language :: Python
Classifier: Programming Language :: Python :: 2
Classifier: Programming Language :: Python :: 2.7
Classifier: Programming Language :: Python :: 3
Classifier: Programming Language :: Python :: 3.3
Classifier: Programming Language :: Python :: 3.4
Classifier: Topic :: Documentation
Classifier: Topic :: Multimedia :: Graphics :: Graphics Conversion
Classifier: Topic :: Office/Business :: Office Suites
Classifier: Topic :: Software Development :: Libraries :: Python Modules
Classifier: Topic :: Utilities
